pyhctb/__init__.py
pyhctb/__main__.py
pyhctb/api.py
pyhctb/exceptions.py
pyhctb-0.0.5.dist-info/LICENSE
pyhctb-0.0.5.dist-info/METADATA
pyhctb-0.0.5.dist-info/WHEEL
pyhctb-0.0.5.dist-info/RECORD
