Metadata-Version: 2.1
Name: pyhctb
Version: 0.0.5
Summary: 
Home-page: https://www.github.com/dmyoung9/pyhctb/
Author: David Young
Author-email: dmyoung9@asu.edu
Requires-Python: >=3.11,<4.0
Classifier: Programming Language :: Python :: 3
Classifier: Programming Language :: Python :: 3.11
Requires-Dist: requests (>=2.31.0,<3.0.0)
Requires-Dist: selenium (>=4.11.2,<5.0.0)
